 gitinsight/__init__.py
 gitinsight/analyzer.py
 gitinsight/cli.py
 gitinsight/utils.py
gitinsight-0.1.dist-info/METADATA
gitinsight-0.1.dist-info/WHEEL
gitinsight-0.1.dist-info/entry_points.txt
gitinsight-0.1.dist-info/top_level.txt
gitinsight-0.1.dist-info/RECORD
