Metadata-Version: 2.2
Name: GitInsight
Version: 0.1
Summary: A CLI tool to analyze Git repositories and provide insights.
Home-page: https://github.com/ktsoaela/GitInsight
Author: Khotso Tsoaela
Author-email: khotso.s.tsoaela@gmail.com
Classifier: Programming Language :: Python :: 3
Classifier: License :: OSI Approved :: MIT License
Classifier: Operating System :: OS Independent
Requires-Dist: gitpython
Requires-Dist: click
Requires-Dist: matplotlib
Requires-Dist: pandas
Dynamic: author
Dynamic: author-email
Dynamic: classifier
Dynamic: description
Dynamic: description-content-type
Dynamic: home-page
Dynamic: requires-dist
Dynamic: summary
